{"homeAlias":"/","nodes":{"/m2205/01-background/":{"id":0,"title":"01-Background","url":"/m2205/01-background/","group":"none","home":false,"outBound":[],"neighbors":[],"backLinks":[],"noteIcon":"","hide":false,"size":0},"/":{"id":1,"title":"01-Course-Information","url":"/","group":"none","home":true,"outBound":[],"neighbors":[],"backLinks":[],"noteIcon":"","hide":false,"size":0},"/m2205/02-experiment1/":{"id":2,"title":"02-Experiment1","url":"/m2205/02-experiment1/","group":"none","home":false,"outBound":[],"neighbors":[],"backLinks":[],"noteIcon":"","hide":false,"size":0},"/m2205/03-experiment2/":{"id":3,"title":"03-Experiment2","url":"/m2205/03-experiment2/","group":"none","home":false,"outBound":[],"neighbors":[],"backLinks":[],"noteIcon":"","hide":false,"size":0},"/m2205/04-experiment3/":{"id":4,"title":"04-Experiment3","url":"/m2205/04-experiment3/","group":"none","home":false,"outBound":[],"neighbors":[],"backLinks":[],"noteIcon":"","hide":false,"size":0},"/m2205/05-experiment4/":{"id":5,"title":"05-Experiment4","url":"/m2205/05-experiment4/","group":"none","home":false,"outBound":[],"neighbors":[],"backLinks":[],"noteIcon":"","hide":false,"size":0},"/m2205/06-experiment5/":{"id":6,"title":"06-Experiment5","url":"/m2205/06-experiment5/","group":"none","home":false,"outBound":[],"neighbors":[],"backLinks":[],"noteIcon":"","hide":false,"size":0},"/m2205/07-references/":{"id":7,"title":"07-References","url":"/m2205/07-references/","group":"none","home":false,"outBound":[],"neighbors":[],"backLinks":[],"noteIcon":"","hide":false,"size":0},"/m2205/index/":{"id":8,"title":"Current Methods in Synthetic Biology for Biomedical Research","url":"/m2205/index/","group":"none","home":false,"outBound":["01-Course-Information","01-Background","02-Experiment1","03-Experiment2","04-Experiment3","05-Experiment4","06-Experiment5","07-References"],"neighbors":[],"backLinks":[],"noteIcon":"","hide":false,"size":0}},"links":[]}